django_matplotlib/__init__.py
django_matplotlib/apps.py
django_matplotlib/conf.py
django_matplotlib/fields.py
django_matplotlib/figures.py
django_matplotlib/forms.py
django_matplotlib/templates/widgets/matplotlib.html
django_matplotlib/tests/__init__.py
django_matplotlib/tests/runtests.py
django_matplotlib/tests/test_settings.py
django_matplotlib/tests/tests.py
django_matplotlib-0.1.dist-info/LICENSE
django_matplotlib-0.1.dist-info/METADATA
django_matplotlib-0.1.dist-info/WHEEL
django_matplotlib-0.1.dist-info/top_level.txt
django_matplotlib-0.1.dist-info/RECORD
