Metadata-Version: 2.1
Name: django-matplotlib
Version: 0.1
Summary: Matplotlib field for Django
Home-page: https://github.com/scidam/django_matplotlib
Author: Dmitry Kislov
Author-email: kislov@easydan.com
License: UNKNOWN
Keywords: django,matplotlib,python
Platform: UNKNOWN
Classifier: Development Status :: 3 - Alpha
Classifier: License :: OSI Approved :: MIT License
Classifier: Operating System :: OS Independent
Classifier: Programming Language :: Python
Classifier: Programming Language :: Python :: 3.5
Classifier: Programming Language :: Python :: 3.6
Classifier: Programming Language :: Python :: 3.7
Classifier: Topic :: Software Development
Classifier: Intended Audience :: Developers
Requires-Python: >=3.5
